README.md
setup.py
Odoo_API_Library/JwtHttp.py
Odoo_API_Library/Util.py
Odoo_API_Library/Validator.py
Odoo_API_Library/__init__.py
Odoo_API_Library/firebase.py
Odoo_API_Library.egg-info/PKG-INFO
Odoo_API_Library.egg-info/SOURCES.txt
Odoo_API_Library.egg-info/dependency_links.txt
Odoo_API_Library.egg-info/not-zip-safe
Odoo_API_Library.egg-info/requires.txt
Odoo_API_Library.egg-info/top_level.txt