Metadata-Version: 2.1
Name: Odoo-API-Library
Version: 1.1.3
Summary: Store user access token for one-time-login
Home-page: https://github.com/HanZawNyein/odoo_rest_api_library
Author: Han Zaw Nyein
Author-email: hanzawnyineonline@gmail.com
License: UNKNOWN
Platform: UNKNOWN
